{"categorie": "OLEAGINEUX", "ciqual": 15000, "ecologicalBalance": {"acidificationTerrestreEtEauxDouces": 0.076412983, "appauvrissementCoucheOzone": 0.46496768, "changementClimatique": 5.7604477, "ecotoxiciteEcosystemesAquatiqueEauDouce": 293.10696, "emballage": "LPDE", "epuisementEau": 158.39707, "epuisementEnergie": 78.338963, "epuisementMineraux": 48.058422, "eutrophisationEauxDouces": 2.4495156, "eutrophisationMarine": 28.147858000000003, "eutrophisationTerrestre": 0.27758114, "formationPhotochimiqueOzone": 28.947007, "particules": 0.58920758, "rayonnementsIonisants": 0.69323859, "scoreEF": 2.0853347, "utilisationSol": 377.30239}, "glutenFree": true, "heatBalance": {"agSature": 4, "calcium": 260, "eau": 4, "energieKcal": 634, "energieKj": 2652, "fer": 3, "fibres": 12, "glucides": 9, "lipides": 51, "proteines": 18, "sel": 0, "sodium": 5, "sucres": 4, "vitamineC": 0, "vitamineD": 0}, "name": "Amande", "pregnantPermission": true, "unitTogramme": -1, "vegan": true}