{"categorie": "SUCRES", "ciqual": 31038, "ecologicalBalance": {"acidificationTerrestreEtEauxDouces": 0.02350989, "appauvrissementCoucheOzone": 0.35937311, "changementClimatique": 1.9276299, "ecotoxiciteEcosystemesAquatiqueEauDouce": 60.452873, "emballage": "Verre", "epuisementEau": 38.326609, "epuisementEnergie": 38.213462, "epuisementMineraux": 5.7930112000000005, "eutrophisationEauxDouces": 0.60907242, "eutrophisationMarine": 7.453698699999999, "eutrophisationTerrestre": 0.084981886, "formationPhotochimiqueOzone": 10.868469, "particules": 0.18363694, "rayonnementsIonisants": 0.82774936, "scoreEF": 0.54271213, "utilisationSol": 29.416914}, "glutenFree": true, "heatBalance": {"agSature": 0, "calcium": 12, "eau": 39, "energieKcal": 245, "energieKj": 1025, "fer": 0, "fibres": 0, "glucides": 60, "lipides": 0, "proteines": 0, "sel": 0, "sodium": 7, "sucres": 60, "vitamineC": 19, "vitamineD": 0}, "name": "Confiture de cerise", "pregnantPermission": true, "unitTogramme": -1, "vegan": true}