{"categorie": "ALCOOL", "ciqual": 5215, "ecologicalBalance": {"acidificationTerrestreEtEauxDouces": 0.0097260211, "appauvrissementCoucheOzone": 0.23811007, "changementClimatique": 1.1430841, "ecotoxiciteEcosystemesAquatiqueEauDouce": 115.33691, "emballage": "Verre", "epuisementEau": 0.36376919, "epuisementEnergie": 23.238124, "epuisementMineraux": 4.6250337, "eutrophisationEauxDouces": 0.27690145, "eutrophisationMarine": 7.2461282, "eutrophisationTerrestre": 0.027380354, "formationPhotochimiqueOzone": 5.5593881, "particules": 0.0977174069999999, "rayonnementsIonisants": 0.49768874, "scoreEF": 0.18559681, "utilisationSol": 9.4218239}, "glutenFree": true, "heatBalance": {"agSature": 0, "calcium": 7, "eau": 87, "energieKcal": 82, "energieKj": 343, "fer": 0, "fibres": 0, "glucides": 4, "lipides": 0, "proteines": 0, "sel": 0, "sodium": 2, "sucres": 0, "vitamineC": 0, "vitamineD": 0}, "name": "Vin blanc", "pregnantPermission": false, "unitTogramme": -1, "vegan": true}