{"categorie": "LEGUMES", "ciqual": 20017, "ecologicalBalance": {"acidificationTerrestreEtEauxDouces": 0.0078171383, "appauvrissementCoucheOzone": 0.18567193, "changementClimatique": 1.1321591, "ecotoxiciteEcosystemesAquatiqueEauDouce": 13.388498, "emballage": "PP", "epuisementEau": 0.40088446, "epuisementEnergie": 31.182189, "epuisementMineraux": 2.5982933, "eutrophisationEauxDouces": 0.15193925, "eutrophisationMarine": 4.8395199, "eutrophisationTerrestre": 0.03266314, "formationPhotochimiqueOzone": 3.2312408, "particules": 0.0670558669999999, "rayonnementsIonisants": 0.94985571, "scoreEF": 0.14295159, "utilisationSol": 33.039833}, "glutenFree": true, "heatBalance": {"agSature": 0, "calcium": 19, "eau": 93, "energieKcal": 20, "energieKj": 87, "fer": 0, "fibres": 2, "glucides": 1, "lipides": 0, "proteines": 1, "sel": 0, "sodium": 39, "sucres": 1, "vitamineC": 9, "vitamineD": 0}, "name": "Chou-fleur cuit", "pregnantPermission": true, "unitTogramme": -1, "vegan": true}