{"categorie": "LAITS", "ciqual": 19201, "ecologicalBalance": {"acidificationTerrestreEtEauxDouces": 0.035535278, "appauvrissementCoucheOzone": 0.082958784, "changementClimatique": 1.6277151, "ecotoxiciteEcosystemesAquatiqueEauDouce": 26.912709, "emballage": "HPDE", "epuisementEau": 1.13355, "epuisementEnergie": 13.835734, "epuisementMineraux": 1.2866695, "eutrophisationEauxDouces": 0.22289614, "eutrophisationMarine": 6.0612953, "eutrophisationTerrestre": 0.15218978, "formationPhotochimiqueOzone": 3.4899044, "particules": 0.25414932, "rayonnementsIonisants": 0.23239432, "scoreEF": 0.22239127, "utilisationSol": 93.463955}, "glutenFree": true, "heatBalance": {"agSature": 1, "calcium": 110, "eau": 89, "energieKcal": 45, "energieKj": 191, "fer": 0, "fibres": 0, "glucides": 4, "lipides": 1, "proteines": 3, "sel": 0, "sodium": 58, "sucres": 4, "vitamineC": 0, "vitamineD": 0}, "name": "Lait de ch\u00e8vre demi-\u00e9cr\u00e9m\u00e9", "pregnantPermission": true, "unitTogramme": -1, "vegan": false}